npc_utils/__init__.py
npc_utils/py.typed
npc_utils-0.1.13.dist-info/LICENSE
npc_utils-0.1.13.dist-info/METADATA
npc_utils-0.1.13.dist-info/WHEEL
npc_utils-0.1.13.dist-info/top_level.txt
npc_utils-0.1.13.dist-info/RECORD
