Metadata-Version: 2.1
Name: npc-utils
Version: 0.1.13
Summary: Collection of MindScope Neuropixels packages, simplifying installation and keeping versions updated.
Author-email: Ben Hardcastle <ben.hardcastle@alleninstitue.org>
License: MIT
Project-URL: Repository, https://github.com/AllenInstitute/npc_utils
Project-URL: Issues, https://github.com/AllenInstitute/npc_utils/issues
Classifier: Development Status :: 3 - Alpha
Classifier: Programming Language :: Python :: 3
Classifier: Programming Language :: Python :: 3.9
Classifier: Programming Language :: Python :: 3.10
Classifier: Programming Language :: Python :: 3.11
Classifier: License :: OSI Approved :: MIT License
Classifier: Operating System :: Microsoft :: Windows
Classifier: Operating System :: POSIX :: Linux
Requires-Python: >=3.9
License-File: LICENSE
Requires-Dist: npc-io >=0.1.26
Requires-Dist: npc-session >=0.1.34
Requires-Dist: npc-lims >=0.1.135
Requires-Dist: npc-sync >=0.1.9
Requires-Dist: npc-mvr >=0.1.3
Requires-Dist: npc-stim >=0.1.6
Requires-Dist: npc-ephys >=0.1.11
Requires-Dist: npc-samstim >=0.1.4
